clustomatic/__init__.py
clustomatic/clustomatic.py
clustomatic-0.1.1.dist-info/AUTHORS.rst
clustomatic-0.1.1.dist-info/LICENSE
clustomatic-0.1.1.dist-info/METADATA
clustomatic-0.1.1.dist-info/WHEEL
clustomatic-0.1.1.dist-info/entry_points.txt
clustomatic-0.1.1.dist-info/top_level.txt
clustomatic-0.1.1.dist-info/RECORD
