Metadata-Version: 2.1
Name: clustomatic
Version: 0.1.1
Summary: clustomatic is a python package that displays a graph of clustered points with a dataframe in entry
Home-page: https://github.com/ulysse-qd/clustomatic
Author: Ulysse Queritet-Diop
Author-email: ulysse-q@evidenceb.com
License: MIT license
Keywords: clustomatic
Platform: UNKNOWN
Classifier: Development Status :: 2 - Pre-Alpha
Classifier: Intended Audience :: Developers
Classifier: License :: OSI Approved :: MIT License
Classifier: Natural Language :: English
Classifier: Programming Language :: Python :: 3
Classifier: Programming Language :: Python :: 3.5
Classifier: Programming Language :: Python :: 3.6
Classifier: Programming Language :: Python :: 3.7
Classifier: Programming Language :: Python :: 3.8
Requires-Python: >=3.5
Requires-Dist: matplotlib
Requires-Dist: numpy
Requires-Dist: pandas
Requires-Dist: scikit-learn
Requires-Dist: wheel
